./.gitignore
./.python-version
./.ruff.toml
./CHANGELOG.md
./CONTRIBUTING.md
./LICENSE
./PKG-INFO
./README.md
./README_zh.md
./__init__.py
./app.py
./cli.py
./exception.py
./install.sh
./mcp.example.yaml
./py.typed
./pyproject.toml
./uv.lock
./.github/pull_request_template.md
./.github/workflows/lint.yml
./.github/workflows/python-package.yml
./.github/workflows/python-publish.yml
./config/__init__.py
./config/app.py
./config/base.py
./config/llm.py
./database/__init__.py
./database/client.py
./database/duckdb_client.py
./database/duckdb_loader.py
./database/errors.py
./database/history.py
./database/schema.py
./database/service.py
./database/types.py
./dev/README.md
./dev/code-style.sh
./dev/pytest.sh
./docs/tutorial.md
./docs/tutorial_zh.md
./docs/assets/img.png
./docs/features/benchmark.md
./docs/features/benchmark_zh.md
./docs/features/execution-plan-analysis.md
./docs/features/execution-plan-analysis_zh.md
./docs/features/mcp.md
./docs/features/mcp_zh.md
./docs/features/research.md
./docs/features/research_zh.md
./docs/scenarios/cloud-rds-management.md
./docs/scenarios/cloud-rds-management_zh.md
./docs/scenarios/local-file-analysis.md
./docs/scenarios/local-file-analysis_zh.md
./docs/scenarios/lock-troubleshooting.md
./docs/scenarios/lock-troubleshooting_zh.md
./docs/scenarios/performance-benchmarking.md
./docs/scenarios/performance-benchmarking_zh.md
./docs/scenarios/schema-analysis.md
./docs/scenarios/schema-analysis_zh.md
./docs/scenarios/slow-query-analysis.md
./docs/scenarios/slow-query-analysis_zh.md
./docs/scenarios/sql-result-explanation.md
./docs/scenarios/sql-result-explanation_zh.md
./events/__init__.py
./events/message.py
./llm/embedding.py
./llm/llm.py
./llm/thinking.py
./loop/__init__.py
./loop/agent.py
./loop/agentspec.py
./loop/compaction.py
./loop/context.py
./loop/neoloop.py
./loop/nodes.py
./loop/runtime.py
./loop/state.py
./loop/toolset.py
./loop/types.py
./prompts/default_agent.yaml
./prompts/explain_agent.yaml
./prompts/explain_system.md
rdsai_cli-0.1.8.dist-info/METADATA
rdsai_cli-0.1.8.dist-info/WHEEL
rdsai_cli-0.1.8.dist-info/entry_points.txt
rdsai_cli-0.1.8.dist-info/licenses/LICENSE
rdsai_cli-0.1.8.dist-info/RECORD
