Metadata-Version: 2.4
Name: rdsai-cli
Version: 0.1.8
Summary: AI-powered CLI tool for Relation database management and analysis
Author-email: "yanpei.wyp" <yanpei.wyp@gmail.com>
License: MIT
License-File: LICENSE
Keywords: ai,cli,database,langchain,mysql
Classifier: Development Status :: 3 - Alpha
Classifier: Environment :: Console
Classifier: Intended Audience :: Developers
Classifier: Intended Audience :: System Administrators
Classifier: License :: OSI Approved :: MIT License
Classifier: Operating System :: OS Independent
Classifier: Programming Language :: Python :: 3
Classifier: Programming Language :: Python :: 3.13
Classifier: Topic :: Database
Classifier: Topic :: Database :: Database Engines/Servers
Classifier: Typing :: Typed
Requires-Python: >=3.13
Requires-Dist: aiohttp>=3.13.0
Requires-Dist: duckdb>=1.4.3
Requires-Dist: fastmcp>=2.13.3
Requires-Dist: langchain-anthropic>=1.2.0
Requires-Dist: langchain-core>=1.1.0
Requires-Dist: langchain-deepseek>=0.1.3
Requires-Dist: langchain-google-genai>=4.0.0
Requires-Dist: langchain-openai>=1.1.0
Requires-Dist: langchain-qwq>=0.3.1
Requires-Dist: langchain>=1.1.0
Requires-Dist: langgraph>=1.0.4
Requires-Dist: loguru>=0.7.0
Requires-Dist: mysql-connector-python>=9.3.0
Requires-Dist: packaging>=24.0
Requires-Dist: prompt-toolkit>=3.0.52
Requires-Dist: pydantic>=2.12.0
Requires-Dist: pyperclip>=1.11.0
Requires-Dist: pyyaml>=6.0.0
Requires-Dist: rich>=14.0.0
Requires-Dist: streamingjson>=0.0.5
Requires-Dist: tenacity>=9.1.0
Requires-Dist: trafilatura>=1.12.0
Requires-Dist: typer>=0.20.0
Provides-Extra: dev
Requires-Dist: mypy>=1.19.0; extra == 'dev'
Requires-Dist: pytest-asyncio>=0.24.0; extra == 'dev'
Requires-Dist: pytest>=8.0.0; extra == 'dev'
Requires-Dist: ruff>=0.14.8; extra == 'dev'
